GSG.py
datasets/__init__.py
datasets/data_util.py
models/__init__.py
models/dot_gat.py
models/edcoder.py
models/gat.py
models/gcn.py
models/gin.py
models/loss_func.py
tools/__init__.py
tools/batch_remove.py
tools/evaluation.py
tools/parameters_dict.py
tools/test.py
tools/utils.py
GSG-0.5.9.dist-info/METADATA
GSG-0.5.9.dist-info/WHEEL
GSG-0.5.9.dist-info/top_level.txt
GSG-0.5.9.dist-info/RECORD
