Metadata-Version: 2.1
Name: GSG
Version: 0.5.9
Home-page: https://github.com/keaml-Guan/GSG
License: MIT Licence
Requires-Python: >=3.8
Requires-Dist: torch ==1.9.0
Requires-Dist: numpy ==1.22.0
Requires-Dist: scanpy ==1.8.2
Requires-Dist: anndata ==0.8.0
Requires-Dist: dgl ==0.9.0
Requires-Dist: pandas ==1.2.4
Requires-Dist: scipy ==1.7.3
Requires-Dist: scikit-learn ==1.0.1
Requires-Dist: tqdm ==4.64.1
Requires-Dist: matplotlib ==3.5.3
Requires-Dist: tensorboardX ==2.5.1
Requires-Dist: pyyaml ==6.0.1
Requires-Dist: plotly ==5.21.0
Requires-Dist: kaleido ==0.2.1
Requires-Dist: igraph ==0.9.8
